<?xml version="1.0" encoding="UTF-8"?><Document xmlns:xsi="http://www.w3.org/2001/XMLSchema-instance" xmlns="urn:iso:std:iso:20022:tech:xsd:camt.053.001.02"><BkToCstmrStmt><GrpHdr><MsgId>0462190935.2025-01-02</MsgId><CreDtTm>2026-05-05T14:59:41.11+02:00</CreDtTm><MsgPgntn><PgNb>1</PgNb><LastPgInd>true</LastPgInd></MsgPgntn></GrpHdr><Stmt><Id>0462190935.2025-01-02</Id><ElctrncSeqNb>000000000000000084</ElctrncSeqNb><CreDtTm>2026-05-05T14:59:41.11+02:00</CreDtTm><Acct><Id><IBAN>NL85ABNA0462190935</IBAN></Id><Ccy>EUR</Ccy><Svcr><FinInstnId><BIC>ABNANL2A</BIC></FinInstnId></Svcr></Acct><Bal><Tp><CdOrPrtry><Cd>PRCD</Cd></CdOrPrtry></Tp><Amt Ccy="EUR">000000000001219.16</Amt><CdtDbtInd>CRDT</CdtDbtInd><Dt><Dt>2024-12-31</Dt></Dt></Bal><Bal><Tp><CdOrPrtry><Cd>CLBD</Cd></CdOrPrtry></Tp><Amt Ccy="EUR">000000000001156.38</Amt><CdtDbtInd>CRDT</CdtDbtInd><Dt><Dt>2025-01-02</Dt></Dt></Bal><Ntry><Amt Ccy="EUR">000000000000062.78</Amt><CdtDbtInd>DBIT</CdtDbtInd><Sts>BOOK</Sts><BookgDt><Dt>2025-01-02</Dt></BookgDt><ValDt><Dt>2025-01-02</Dt></ValDt><AcctSvcrRef>4365V4352861703S0AD</AcctSvcrRef><BkTxCd><Domn><Cd>PMNT</Cd><Fmly><Cd>RDDT</Cd><SubFmlyCd>ESDD</SubFmlyCd></Fmly></Domn><Prtry><Cd>N247</Cd><Issr>ABNAMRO</Issr></Prtry></BkTxCd><NtryDtls><TxDtls><Refs><MsgId>NCOR2412310902340000000000000000016</MsgId><AcctSvcrRef>4365V4352861703S0AD</AcctSvcrRef><EndToEndId>1039299073926</EndToEndId><MndtId>4FJJ22564WFSG</MndtId></Refs><AmtDtls><TxAmt><Amt Ccy="EUR">000000000000062.78</Amt></TxAmt></AmtDtls><RltdPties><Cdtr><Nm>PayPal Europe S.a.r.l. e</Nm><PstlAdr><Ctry>LU</Ctry></PstlAdr></Cdtr><CdtrAcct><Id><IBAN>LU89751000135104200E</IBAN></Id></CdtrAcct></RltdPties><RltdAgts><DbtrAgt><FinInstnId><BIC>ABNANL2A</BIC></FinInstnId></DbtrAgt><CdtrAgt><FinInstnId><BIC>PPLXLUL2</BIC></FinInstnId></CdtrAgt></RltdAgts><RmtInf><Ustrd>1039299073926/PAYPAL</Ustrd></RmtInf></TxDtls></NtryDtls><AddtlNtryInf>/TRTP/SEPA Incasso algemeen doorlopend/CSID/LU96ZZZ0000000000000000058/NAME/PayPal Europe S.a.r.l. et Cie S.C.A/MARF/4FJJ22564WFSG/REMI/1039299073926/PAYPAL/IBAN/LU89751000135104200E/BIC/PPLXLUL2/EREF/1039299073926</AddtlNtryInf></Ntry></Stmt></BkToCstmrStmt></Document>                                                                                                                                                                                                                                                                                                                                                                                                                                                                                                                                                                                                                                                                                                                                                                                                                                                                                                                                                                                                                                                                                                                                                                                                                                                                                                                                                                                                                                                                                                                                                                                                                                                                                                                                                                                                                                                                                                                                                                                                                                                                                                                                                                                                                                                                                                                                                                                                                                                                                                                                                                                                                                                                                                                                                                                                                                                                                                                                                                                                                                                                                                                                                                                                                                                                                                                                                                                                                                                                                                                                                                                                                                                                                                                                                                                                                                                                                                                                                                                                                                                                                                                                                                                                                                                                                                                                                                                                                                                                                                                                                                                                                                                                                                                                                                                                                                                                                                                                                                                                                                                                                                                                                                                                                                                                                                                                                                                                                                                                                                                                                                                                                                                                                                                                                                                                                                                                                                                                                                                                                                                                                                                                                                                                                                                                                                                                                                                                                                                                                                                                                                                                                                                                                                                                                                                                                                                                                                                                                                                                                                                                                                                                                                                                                                                                                                                                                                                                                                                                                                                                                                                                                                                                                                                                                                                                                                                                                                                                                                                                                                                                                                                                                                                                                                                                                                                                                                                                                                                                                                                                                                                                                                                                                                                                                                                                                                                                                                                                                                                                                                                                                                                                                                                                                                                                                                                                                                                                                                                                                                                                                                                                                                                                                                                                                                                                                                                                                                                                                                                                                                                                                                                                                                                                                                                                                                                                                                                                                                                                                                                                                                                                                                                                                                                                                                                                                                                                                                                                                                                                                                                                                                                                                                                                                                                                                                                                                                                                                                                                                                                                                                                                                                                                                                                                                                                                                                                                                                                                                                                                                                                                                                                                                                                                                                                                                                                                                                                                                                                                                                                                                                                                                                                                                                                                                                                                                                                                                                                                                                                                                                                                                                                                                                                                                                                                                                                                                                                                                                                                                                                                                                                                                                                                                                                                                                                                                                                                                                                                                                                                                                                                                                                                                                                                                                                                                                                                                                                                                                                                                                                                                                                                                                                                                                                                                                                                                                                                                                                                                                                                                                                                                                                                                                                                                                                                                                                                                                                                                                                                                                                                                                                                                                                                                                                                                                                                                                                                                                                                                                                                                                                                                                                                                                                                                                                                                                                                                                                                                                                                                                                                                                                                                                                                                                                                                                                                                                                                                                                                                                                                                                                                                                                                                                                                                                                                                                                                                                                                                                                                                                                                                                                                                                                                                                                                                                                                                                                                                                                                                                                                                                                                                                                                                                                                                                                                                                                                                                                                                                                                                                                                                                                                                                                                                                                                                                                                                                                                                                                                                                                                                                                                                                                                                                                                                                                                                                                                                                                                                                                                                                                                                                                                                                                                                                                                                                                                                                                                                                                                                                                                                                                                                                                                                                                                                                                                                                                                                                                                                                                                                                                                                                                                                                                                                                                                                                                                                                                                                                                                                                                                                                                                                                                                                                                                                                                                                                                                                                                                                                                                                                                                                                                                                                                                                                                                                                                                                                                                                                                                                                                                                                                                                                                                                                                                                                                                                                                                                                                                                                                                                                                                                                                                                                                                                                                                                                                                                                                                                                                                                                                                                                                                                                                                                                                                                                                                                                                                                                                                                                                                                                                                                                                                                                                                                                                                                                                                                                                                                                                                                                                                                                                                                                                                                                                                                                                                                                                                                                                                                                                                                                                                                                                                                                                                                                                                                                                                                                                                                                                                                                                                                                                                                                                                                                                                                                                                                                                                                                                                                                                                                                                                                                                                                                                                                                                                                                                                                                                                                                                                                                                                                                                                                                                                                                                                                                                                                                                                                                                                                                                                                                                                                                                                                                                                                                                                                                                                                                                                                                                                                                                                                                                                                                                                                                                                                                                                                                                                                                                                                                                                                                                                                                                                                                                                                                                                                                                                                                                                                                                                                                                                                                                                                                                                                                                                                                                                                                                                                                                                                                                                                                                                                                                                                                                                                                                                                                                                                                                                                                                                                                                                                                                                                                                                                                                                                                                                                                                                                                                                                                                                                                                                                                                                                                                                                                                                                                                                                                                                                                                                                                                                                                                                                                                                                                                                                                                                                                                                                                                                                                                                                                                                                                                                                                                                                                                                                                                                                                                                                                                                                                                                                                                                                                                                                                                                                                                                                                                                                                                                                                                                                                                                                                                      